energyquantified/__init__.py
energyquantified/__version__.py
energyquantified/base.py
energyquantified/api/__init__.py
energyquantified/api/base.py
energyquantified/api/events.py
energyquantified/api/instances.py
energyquantified/api/metadata.py
energyquantified/api/ohlc.py
energyquantified/api/period_instances.py
energyquantified/api/periods.py
energyquantified/api/srmc.py
energyquantified/api/timeseries.py
energyquantified/api/user.py
energyquantified/data/__init__.py
energyquantified/data/absolute.py
energyquantified/data/base.py
energyquantified/data/ohlc.py
energyquantified/data/periodseries.py
energyquantified/data/srmc.py
energyquantified/data/timeseries.py
energyquantified/events/__init__.py
energyquantified/events/callback.py
energyquantified/events/connection_event.py
energyquantified/events/event_options.py
energyquantified/events/event_type.py
energyquantified/events/events.py
energyquantified/events/responses.py
energyquantified/events/messages/__init__.py
energyquantified/events/messages/constants.py
energyquantified/events/messages/validations.py
energyquantified/events/messages/client/__init__.py
energyquantified/events/messages/client/base_request.py
energyquantified/events/messages/client/curve_filters.py
energyquantified/events/messages/client/subscribe_curves.py
energyquantified/events/messages/server/__init__.py
energyquantified/events/messages/server/base.py
energyquantified/events/messages/server/server_message_type.py
energyquantified/events/messages/server/messages/__init__.py
energyquantified/events/messages/server/messages/event.py
energyquantified/events/messages/server/messages/message.py
energyquantified/events/messages/server/responses/__init__.py
energyquantified/events/messages/server/responses/base_response.py
energyquantified/events/messages/server/responses/curves_filters.py
energyquantified/events/messages/server/responses/curves_subscribe.py
energyquantified/events/messages/server/responses/error.py
energyquantified-0.15.dist-info/LICENSE
energyquantified-0.15.dist-info/METADATA
energyquantified-0.15.dist-info/WHEEL
energyquantified-0.15.dist-info/top_level.txt
energyquantified-0.15.dist-info/RECORD
