Metadata-Version: 2.1
Name: energyquantified
Version: 0.15
Summary: Energy Quantified Time series API client.
Home-page: https://github.com/energyquantified/eq-python-client
Author: Energy Quantified AS
License: UNKNOWN
Project-URL: Documentation, https://energyquantified-python.readthedocs.io
Project-URL: Source, https://github.com/energyquantified/eq-python-client
Platform: UNKNOWN
Classifier: Development Status :: 4 - Beta
Classifier: Environment :: Console
Classifier: Intended Audience :: Developers
Classifier: Intended Audience :: Science/Research
Classifier: Intended Audience :: Financial and Insurance Industry
Classifier: License :: OSI Approved :: Apache Software License
Classifier: Natural Language :: English
Classifier: Operating System :: Microsoft :: Windows
Classifier: Operating System :: POSIX :: Linux
Classifier: Programming Language :: Python :: 3
Classifier: Programming Language :: Python :: 3.10
Classifier: Programming Language :: Python :: 3.11
Classifier: Programming Language :: Python :: 3.12
Classifier: Programming Language :: Python :: 3.13
Classifier: Topic :: Office/Business :: Financial
Classifier: Topic :: Software Development :: Libraries :: Python Modules
Requires-Python: >=3.10
License-File: LICENSE
Requires-Dist: python-dateutil<2.10,>=2.8.0
Requires-Dist: pytz
Requires-Dist: requests<3,>=2.31
Requires-Dist: tzlocal
Requires-Dist: websocket-client<2,>=1.5.1
